{
	"configurations" : 
	[
		{
			"directories" : 
			[
				{
					"build" : ".",
					"childIndexes" : 
					[
						1,
						2
					],
					"jsonFile" : "directory-.-Release-f5ebdc15457944623624.json",
					"minimumCMakeVersion" : 
					{
						"string" : "3.18"
					},
					"projectIndex" : 0,
					"source" : "."
				},
				{
					"build" : "hal",
					"jsonFile" : "directory-hal-Release-b0ca0e3cac237c9cce65.json",
					"minimumCMakeVersion" : 
					{
						"string" : "3.18"
					},
					"parentIndex" : 0,
					"projectIndex" : 0,
					"source" : "hal",
					"targetIndexes" : 
					[
						0
					]
				},
				{
					"build" : "app",
					"jsonFile" : "directory-app-Release-94c5f210ca04b1028ae5.json",
					"minimumCMakeVersion" : 
					{
						"string" : "3.18"
					},
					"parentIndex" : 0,
					"projectIndex" : 0,
					"source" : "app",
					"targetIndexes" : 
					[
						1
					]
				}
			],
			"name" : "Release",
			"projects" : 
			[
				{
					"directoryIndexes" : 
					[
						0,
						1,
						2
					],
					"name" : "reaction_timer",
					"targetIndexes" : 
					[
						0,
						1
					]
				}
			],
			"targets" : 
			[
				{
					"directoryIndex" : 1,
					"id" : "hal::@ad971efe0e95b39e260f",
					"jsonFile" : "target-hal-Release-b57dcaa6dd92166212b2.json",
					"name" : "hal",
					"projectIndex" : 0
				},
				{
					"directoryIndex" : 2,
					"id" : "reaction_timer::@5f5a17c01335469806cb",
					"jsonFile" : "target-reaction_timer-Release-a802909aea143f6727dd.json",
					"name" : "reaction_timer",
					"projectIndex" : 0
				}
			]
		}
	],
	"kind" : "codemodel",
	"paths" : 
	{
		"build" : "/home/junpinfoo/cmpt433/work/CMPT433/as1/build",
		"source" : "/home/junpinfoo/cmpt433/work/CMPT433/as1"
	},
	"version" : 
	{
		"major" : 2,
		"minor" : 4
	}
}
